LICENSE
README.md
setup.py
extrempy/__init__.py
extrempy/constant.py
extrempy/dataset.py
extrempy/dpsample.py
extrempy/dptest.py
extrempy/mdsys.py
extrempy.egg-info/PKG-INFO
extrempy.egg-info/SOURCES.txt
extrempy.egg-info/dependency_links.txt
extrempy.egg-info/not-zip-safe
extrempy.egg-info/top_level.txt